firesoft/__init__.py
firesoft/fire_barcodes.py
firesoft/fire_pil_image_utils.py
firesoft/geometry.py
firesoft/utils/__init__.py
firesoft/utils/files.py
firesoft/utils/qr_code.py
firesoft-0.0.9.dist-info/METADATA
firesoft-0.0.9.dist-info/WHEEL
firesoft-0.0.9.dist-info/top_level.txt
firesoft-0.0.9.dist-info/RECORD
